rdflib_store_trigdump/__init__.py
rdflib_store_trigdump-1.0.0.dist-info/entry_points.txt
rdflib_store_trigdump-1.0.0.dist-info/LICENSE
rdflib_store_trigdump-1.0.0.dist-info/WHEEL
rdflib_store_trigdump-1.0.0.dist-info/METADATA
rdflib_store_trigdump-1.0.0.dist-info/RECORD
